<?xml version="1.0" encoding="utf-8"?>
<!DOCTYPE hibernate-mapping PUBLIC "-//Hibernate/Hibernate Mapping DTD 3.0//EN"
"http://hibernate.sourceforge.net/hibernate-mapping-3.0.dtd">
<!-- 
    Mapping file autogenerated by MyEclipse Persistence Tools
-->
<hibernate-mapping>
    <class name="cn.superion.equipment.entity.EqCurrentRcptNo" table="EQ_CURRENT_RCPT_NO">
        <id name="autoId" type="java.lang.String">
            <column name="AUTO_ID" length="22" />
            <generator class="sequence">
            	<param name="sequence">SEQ_EQ_CURRENT_RCPT_NO</param>
            </generator>
        </id>
        <property name="unitsCode" type="java.lang.String">
            <column name="UNITS_CODE" length="10" not-null="true" />
        </property>
        <property name="rcptFlag" type="java.lang.String">
            <column name="RCPT_FLAG" length="1" not-null="true" />
        </property>
        <property name="rcptType" type="java.lang.String">
            <column name="RCPT_TYPE" length="1" not-null="true" />
        </property>
        <property name="typeDate" type="java.lang.String">
            <column name="TYPE_DATE" length="10" not-null="true" />
        </property>
        <property name="currentNo" type="java.lang.String">
            <column name="CURRENT_NO" length="20" not-null="true" />
        </property>
    </class>
</hibernate-mapping>
